{
  "id": "mm9zps50zajt",
  "name": "2",
  "type": "retention",
  "points": [
    {
      "day": 1,
      "value": 100
    },
    {
      "day": 2,
      "value": 35
    },
    {
      "day": 3,
      "value": 31.269999999999996
    },
    {
      "day": 4,
      "value": 28.93
    },
    {
      "day": 5,
      "value": 26.87
    },
    {
      "day": 6,
      "value": 25.840000000000003
    },
    {
      "day": 7,
      "value": 23.87
    },
    {
      "day": 8,
      "value": 22
    },
    {
      "day": 9,
      "value": 21.81
    },
    {
      "day": 10,
      "value": 22.15
    },
    {
      "day": 11,
      "value": 19.77
    },
    {
      "day": 12,
      "value": 19.650000000000002
    },
    {
      "day": 13,
      "value": 18.88
    },
    {
      "day": 14,
      "value": 19.12
    },
    {
      "day": 15,
      "value": 19.09
    },
    {
      "day": 16,
      "value": 17.88
    },
    {
      "day": 17,
      "value": 17.65
    },
    {
      "day": 18,
      "value": 17.380000000000003
    },
    {
      "day": 19,
      "value": 17.94
    },
    {
      "day": 20,
      "value": 17.32
    },
    {
      "day": 21,
      "value": 17.599999999999998
    },
    {
      "day": 22,
      "value": 16.439999999999998
    },
    {
      "day": 23,
      "value": 17.150000000000002
    },
    {
      "day": 24,
      "value": 16.79
    },
    {
      "day": 25,
      "value": 16.33
    },
    {
      "day": 26,
      "value": 16.31
    },
    {
      "day": 27,
      "value": 15.790000000000001
    },
    {
      "day": 28,
      "value": 16.189999999999998
    },
    {
      "day": 29,
      "value": 17.06
    },
    {
      "day": 30,
      "value": 15.620000000000001
    },
    {
      "day": 31,
      "value": 15
    },
    {
      "day": 32,
      "value": 15.049999999999999
    },
    {
      "day": 33,
      "value": 14.790000000000001
    },
    {
      "day": 34,
      "value": 14.92
    },
    {
      "day": 35,
      "value": 13.889999999999999
    },
    {
      "day": 36,
      "value": 13.65
    },
    {
      "day": 37,
      "value": 13.930000000000001
    },
    {
      "day": 38,
      "value": 13.309999999999999
    },
    {
      "day": 39,
      "value": 13.639999999999999
    },
    {
      "day": 40,
      "value": 13.11
    },
    {
      "day": 41,
      "value": 13.100000000000001
    },
    {
      "day": 42,
      "value": 13.209999999999999
    },
    {
      "day": 43,
      "value": 12.620000000000001
    },
    {
      "day": 44,
      "value": 12.73
    },
    {
      "day": 45,
      "value": 12.879999999999999
    },
    {
      "day": 46,
      "value": 12.870000000000001
    },
    {
      "day": 47,
      "value": 12.809999999999999
    },
    {
      "day": 48,
      "value": 12.64
    },
    {
      "day": 49,
      "value": 12.58
    },
    {
      "day": 50,
      "value": 11.82
    },
    {
      "day": 51,
      "value": 12.1
    },
    {
      "day": 52,
      "value": 11.690000000000001
    },
    {
      "day": 53,
      "value": 12.35
    },
    {
      "day": 54,
      "value": 11.5
    },
    {
      "day": 55,
      "value": 12.09
    },
    {
      "day": 56,
      "value": 12.16
    },
    {
      "day": 57,
      "value": 11.95
    },
    {
      "day": 58,
      "value": 11.53
    },
    {
      "day": 59,
      "value": 11.4
    },
    {
      "day": 60,
      "value": 11.26
    },
    {
      "day": 61,
      "value": 11.03
    },
    {
      "day": 62,
      "value": 10.8
    },
    {
      "day": 63,
      "value": 10.9
    },
    {
      "day": 64,
      "value": 11.1
    },
    {
      "day": 65,
      "value": 10.45
    },
    {
      "day": 66,
      "value": 10.290000000000001
    },
    {
      "day": 67,
      "value": 10.190000000000001
    },
    {
      "day": 68,
      "value": 10.39
    },
    {
      "day": 69,
      "value": 9.99
    },
    {
      "day": 70,
      "value": 9.81
    },
    {
      "day": 71,
      "value": 10.08
    },
    {
      "day": 72,
      "value": 9.62
    },
    {
      "day": 73,
      "value": 9.610000000000001
    },
    {
      "day": 74,
      "value": 9.59
    },
    {
      "day": 75,
      "value": 9.69
    },
    {
      "day": 76,
      "value": 9.24
    },
    {
      "day": 77,
      "value": 9.33
    },
    {
      "day": 78,
      "value": 8.86
    },
    {
      "day": 79,
      "value": 8.91
    },
    {
      "day": 80,
      "value": 9.24
    },
    {
      "day": 81,
      "value": 9.21
    },
    {
      "day": 82,
      "value": 8.58
    },
    {
      "day": 83,
      "value": 9.02
    },
    {
      "day": 84,
      "value": 8.85
    },
    {
      "day": 85,
      "value": 8.84
    },
    {
      "day": 86,
      "value": 8.450000000000001
    },
    {
      "day": 87,
      "value": 8.6
    },
    {
      "day": 88,
      "value": 8.81
    },
    {
      "day": 89,
      "value": 8.16
    },
    {
      "day": 90,
      "value": 8.200000000000001
    },
    {
      "day": 91,
      "value": 8.51
    },
    {
      "day": 92,
      "value": 8.459999999999999
    },
    {
      "day": 93,
      "value": 8.41
    },
    {
      "day": 94,
      "value": 8.36
    },
    {
      "day": 95,
      "value": 8.309999999999999
    },
    {
      "day": 96,
      "value": 8.260000000000002
    },
    {
      "day": 97,
      "value": 8.21
    },
    {
      "day": 98,
      "value": 8.16
    },
    {
      "day": 99,
      "value": 8.110000000000001
    },
    {
      "day": 100,
      "value": 8.06
    },
    {
      "day": 101,
      "value": 8.01
    },
    {
      "day": 102,
      "value": 7.960000000000001
    },
    {
      "day": 103,
      "value": 7.91
    },
    {
      "day": 104,
      "value": 7.86
    },
    {
      "day": 105,
      "value": 7.8100000000000005
    },
    {
      "day": 106,
      "value": 7.7700000000000005
    },
    {
      "day": 107,
      "value": 7.720000000000001
    },
    {
      "day": 108,
      "value": 7.670000000000001
    },
    {
      "day": 109,
      "value": 7.630000000000001
    },
    {
      "day": 110,
      "value": 7.580000000000001
    },
    {
      "day": 111,
      "value": 7.539999999999999
    },
    {
      "day": 112,
      "value": 7.489999999999999
    },
    {
      "day": 113,
      "value": 7.4399999999999995
    },
    {
      "day": 114,
      "value": 7.3999999999999995
    },
    {
      "day": 115,
      "value": 7.35
    },
    {
      "day": 116,
      "value": 7.31
    },
    {
      "day": 117,
      "value": 7.2700000000000005
    },
    {
      "day": 118,
      "value": 7.22
    },
    {
      "day": 119,
      "value": 7.180000000000001
    },
    {
      "day": 120,
      "value": 7.140000000000001
    },
    {
      "day": 121,
      "value": 7.090000000000001
    },
    {
      "day": 122,
      "value": 7.049999999999999
    },
    {
      "day": 123,
      "value": 7.01
    },
    {
      "day": 124,
      "value": 6.97
    },
    {
      "day": 125,
      "value": 6.92
    },
    {
      "day": 126,
      "value": 6.88
    },
    {
      "day": 127,
      "value": 6.84
    },
    {
      "day": 128,
      "value": 6.800000000000001
    },
    {
      "day": 129,
      "value": 6.76
    },
    {
      "day": 130,
      "value": 6.72
    },
    {
      "day": 131,
      "value": 6.68
    },
    {
      "day": 132,
      "value": 6.64
    },
    {
      "day": 133,
      "value": 6.6000000000000005
    },
    {
      "day": 134,
      "value": 6.5600000000000005
    },
    {
      "day": 135,
      "value": 6.52
    },
    {
      "day": 136,
      "value": 6.4799999999999995
    },
    {
      "day": 137,
      "value": 6.4399999999999995
    },
    {
      "day": 138,
      "value": 6.4
    },
    {
      "day": 139,
      "value": 6.36
    },
    {
      "day": 140,
      "value": 6.329999999999999
    },
    {
      "day": 141,
      "value": 6.29
    },
    {
      "day": 142,
      "value": 6.25
    },
    {
      "day": 143,
      "value": 6.21
    },
    {
      "day": 144,
      "value": 6.18
    },
    {
      "day": 145,
      "value": 6.140000000000001
    },
    {
      "day": 146,
      "value": 6.1
    },
    {
      "day": 147,
      "value": 6.069999999999999
    },
    {
      "day": 148,
      "value": 6.03
    },
    {
      "day": 149,
      "value": 6
    },
    {
      "day": 150,
      "value": 5.96
    },
    {
      "day": 151,
      "value": 5.92
    },
    {
      "day": 152,
      "value": 5.89
    },
    {
      "day": 153,
      "value": 5.8500000000000005
    },
    {
      "day": 154,
      "value": 5.82
    },
    {
      "day": 155,
      "value": 5.79
    },
    {
      "day": 156,
      "value": 5.75
    },
    {
      "day": 157,
      "value": 5.72
    },
    {
      "day": 158,
      "value": 5.680000000000001
    },
    {
      "day": 159,
      "value": 5.65
    },
    {
      "day": 160,
      "value": 5.62
    },
    {
      "day": 161,
      "value": 5.58
    },
    {
      "day": 162,
      "value": 5.55
    },
    {
      "day": 163,
      "value": 5.52
    },
    {
      "day": 164,
      "value": 5.48
    },
    {
      "day": 165,
      "value": 5.45
    },
    {
      "day": 166,
      "value": 5.42
    },
    {
      "day": 167,
      "value": 5.390000000000001
    },
    {
      "day": 168,
      "value": 5.36
    },
    {
      "day": 169,
      "value": 5.319999999999999
    },
    {
      "day": 170,
      "value": 5.29
    },
    {
      "day": 171,
      "value": 5.26
    },
    {
      "day": 172,
      "value": 5.2299999999999995
    },
    {
      "day": 173,
      "value": 5.2
    },
    {
      "day": 174,
      "value": 5.17
    },
    {
      "day": 175,
      "value": 5.140000000000001
    },
    {
      "day": 176,
      "value": 5.11
    },
    {
      "day": 177,
      "value": 5.08
    },
    {
      "day": 178,
      "value": 5.050000000000001
    },
    {
      "day": 179,
      "value": 5.0200000000000005
    },
    {
      "day": 180,
      "value": 4.99
    },
    {
      "day": 181,
      "value": 4.97
    },
    {
      "day": 182,
      "value": 4.9399999999999995
    },
    {
      "day": 183,
      "value": 4.91
    },
    {
      "day": 184,
      "value": 4.89
    },
    {
      "day": 185,
      "value": 4.859999999999999
    },
    {
      "day": 186,
      "value": 4.83
    },
    {
      "day": 187,
      "value": 4.81
    },
    {
      "day": 188,
      "value": 4.78
    },
    {
      "day": 189,
      "value": 4.760000000000001
    },
    {
      "day": 190,
      "value": 4.73
    },
    {
      "day": 191,
      "value": 4.71
    },
    {
      "day": 192,
      "value": 4.68
    },
    {
      "day": 193,
      "value": 4.66
    },
    {
      "day": 194,
      "value": 4.63
    },
    {
      "day": 195,
      "value": 4.61
    },
    {
      "day": 196,
      "value": 4.58
    },
    {
      "day": 197,
      "value": 4.5600000000000005
    },
    {
      "day": 198,
      "value": 4.53
    },
    {
      "day": 199,
      "value": 4.51
    },
    {
      "day": 200,
      "value": 4.4799999999999995
    },
    {
      "day": 201,
      "value": 4.46
    },
    {
      "day": 202,
      "value": 4.43
    },
    {
      "day": 203,
      "value": 4.41
    },
    {
      "day": 204,
      "value": 4.38
    },
    {
      "day": 205,
      "value": 4.36
    },
    {
      "day": 206,
      "value": 4.34
    },
    {
      "day": 207,
      "value": 4.31
    },
    {
      "day": 208,
      "value": 4.29
    },
    {
      "day": 209,
      "value": 4.26
    },
    {
      "day": 210,
      "value": 4.24
    },
    {
      "day": 211,
      "value": 4.22
    },
    {
      "day": 212,
      "value": 4.19
    },
    {
      "day": 213,
      "value": 4.17
    },
    {
      "day": 214,
      "value": 4.15
    },
    {
      "day": 215,
      "value": 4.12
    },
    {
      "day": 216,
      "value": 4.1000000000000005
    },
    {
      "day": 217,
      "value": 4.08
    },
    {
      "day": 218,
      "value": 4.06
    },
    {
      "day": 219,
      "value": 4.03
    },
    {
      "day": 220,
      "value": 4.01
    },
    {
      "day": 221,
      "value": 3.9899999999999998
    },
    {
      "day": 222,
      "value": 3.9699999999999998
    },
    {
      "day": 223,
      "value": 3.94
    },
    {
      "day": 224,
      "value": 3.92
    },
    {
      "day": 225,
      "value": 3.9
    },
    {
      "day": 226,
      "value": 3.88
    },
    {
      "day": 227,
      "value": 3.8600000000000003
    },
    {
      "day": 228,
      "value": 3.83
    },
    {
      "day": 229,
      "value": 3.81
    },
    {
      "day": 230,
      "value": 3.7900000000000005
    },
    {
      "day": 231,
      "value": 3.7699999999999996
    },
    {
      "day": 232,
      "value": 3.75
    },
    {
      "day": 233,
      "value": 3.73
    },
    {
      "day": 234,
      "value": 3.71
    },
    {
      "day": 235,
      "value": 3.6799999999999997
    },
    {
      "day": 236,
      "value": 3.66
    },
    {
      "day": 237,
      "value": 3.64
    },
    {
      "day": 238,
      "value": 3.62
    },
    {
      "day": 239,
      "value": 3.5999999999999996
    },
    {
      "day": 240,
      "value": 3.58
    },
    {
      "day": 241,
      "value": 3.56
    },
    {
      "day": 242,
      "value": 3.54
    },
    {
      "day": 243,
      "value": 3.52
    },
    {
      "day": 244,
      "value": 3.5000000000000004
    },
    {
      "day": 245,
      "value": 3.4799999999999995
    },
    {
      "day": 246,
      "value": 3.46
    },
    {
      "day": 247,
      "value": 3.44
    },
    {
      "day": 248,
      "value": 3.42
    },
    {
      "day": 249,
      "value": 3.4000000000000004
    },
    {
      "day": 250,
      "value": 3.38
    },
    {
      "day": 251,
      "value": 3.36
    },
    {
      "day": 252,
      "value": 3.34
    },
    {
      "day": 253,
      "value": 3.32
    },
    {
      "day": 254,
      "value": 3.3000000000000003
    },
    {
      "day": 255,
      "value": 3.2800000000000002
    },
    {
      "day": 256,
      "value": 3.27
    },
    {
      "day": 257,
      "value": 3.25
    },
    {
      "day": 258,
      "value": 3.2300000000000004
    },
    {
      "day": 259,
      "value": 3.2099999999999995
    },
    {
      "day": 260,
      "value": 3.19
    },
    {
      "day": 261,
      "value": 3.17
    },
    {
      "day": 262,
      "value": 3.15
    },
    {
      "day": 263,
      "value": 3.1399999999999997
    },
    {
      "day": 264,
      "value": 3.1199999999999997
    },
    {
      "day": 265,
      "value": 3.1
    },
    {
      "day": 266,
      "value": 3.08
    },
    {
      "day": 267,
      "value": 3.06
    },
    {
      "day": 268,
      "value": 3.05
    },
    {
      "day": 269,
      "value": 3.0300000000000002
    },
    {
      "day": 270,
      "value": 3.01
    },
    {
      "day": 271,
      "value": 2.9899999999999998
    },
    {
      "day": 272,
      "value": 2.98
    },
    {
      "day": 273,
      "value": 2.96
    },
    {
      "day": 274,
      "value": 2.94
    },
    {
      "day": 275,
      "value": 2.92
    },
    {
      "day": 276,
      "value": 2.91
    },
    {
      "day": 277,
      "value": 2.8899999999999997
    },
    {
      "day": 278,
      "value": 2.87
    },
    {
      "day": 279,
      "value": 2.86
    },
    {
      "day": 280,
      "value": 2.8400000000000003
    },
    {
      "day": 281,
      "value": 2.82
    },
    {
      "day": 282,
      "value": 2.81
    },
    {
      "day": 283,
      "value": 2.79
    },
    {
      "day": 284,
      "value": 2.77
    },
    {
      "day": 285,
      "value": 2.76
    },
    {
      "day": 286,
      "value": 2.74
    },
    {
      "day": 287,
      "value": 2.73
    },
    {
      "day": 288,
      "value": 2.71
    },
    {
      "day": 289,
      "value": 2.69
    },
    {
      "day": 290,
      "value": 2.68
    },
    {
      "day": 291,
      "value": 2.6599999999999997
    },
    {
      "day": 292,
      "value": 2.65
    },
    {
      "day": 293,
      "value": 2.63
    },
    {
      "day": 294,
      "value": 2.62
    },
    {
      "day": 295,
      "value": 2.6
    },
    {
      "day": 296,
      "value": 2.59
    },
    {
      "day": 297,
      "value": 2.5700000000000003
    },
    {
      "day": 298,
      "value": 2.55
    },
    {
      "day": 299,
      "value": 2.54
    },
    {
      "day": 300,
      "value": 2.52
    },
    {
      "day": 301,
      "value": 2.5100000000000002
    },
    {
      "day": 302,
      "value": 2.5
    },
    {
      "day": 303,
      "value": 2.48
    },
    {
      "day": 304,
      "value": 2.4699999999999998
    },
    {
      "day": 305,
      "value": 2.45
    },
    {
      "day": 306,
      "value": 2.44
    },
    {
      "day": 307,
      "value": 2.42
    },
    {
      "day": 308,
      "value": 2.41
    },
    {
      "day": 309,
      "value": 2.39
    },
    {
      "day": 310,
      "value": 2.3800000000000003
    },
    {
      "day": 311,
      "value": 2.37
    },
    {
      "day": 312,
      "value": 2.35
    },
    {
      "day": 313,
      "value": 2.34
    },
    {
      "day": 314,
      "value": 2.33
    },
    {
      "day": 315,
      "value": 2.31
    },
    {
      "day": 316,
      "value": 2.3
    },
    {
      "day": 317,
      "value": 2.2800000000000002
    },
    {
      "day": 318,
      "value": 2.27
    },
    {
      "day": 319,
      "value": 2.26
    },
    {
      "day": 320,
      "value": 2.2399999999999998
    },
    {
      "day": 321,
      "value": 2.23
    },
    {
      "day": 322,
      "value": 2.22
    },
    {
      "day": 323,
      "value": 2.21
    },
    {
      "day": 324,
      "value": 2.19
    },
    {
      "day": 325,
      "value": 2.18
    },
    {
      "day": 326,
      "value": 2.17
    },
    {
      "day": 327,
      "value": 2.15
    },
    {
      "day": 328,
      "value": 2.1399999999999997
    },
    {
      "day": 329,
      "value": 2.13
    },
    {
      "day": 330,
      "value": 2.12
    },
    {
      "day": 331,
      "value": 2.1
    },
    {
      "day": 332,
      "value": 2.09
    },
    {
      "day": 333,
      "value": 2.08
    },
    {
      "day": 334,
      "value": 2.07
    },
    {
      "day": 335,
      "value": 2.06
    },
    {
      "day": 336,
      "value": 2.04
    },
    {
      "day": 337,
      "value": 2.03
    },
    {
      "day": 338,
      "value": 2.02
    },
    {
      "day": 339,
      "value": 2.01
    },
    {
      "day": 340,
      "value": 2
    },
    {
      "day": 341,
      "value": 1.9800000000000002
    },
    {
      "day": 342,
      "value": 1.97
    },
    {
      "day": 343,
      "value": 1.96
    },
    {
      "day": 344,
      "value": 1.95
    },
    {
      "day": 345,
      "value": 1.94
    },
    {
      "day": 346,
      "value": 1.9300000000000002
    },
    {
      "day": 347,
      "value": 1.92
    },
    {
      "day": 348,
      "value": 1.91
    },
    {
      "day": 349,
      "value": 1.8900000000000001
    },
    {
      "day": 350,
      "value": 1.8800000000000001
    },
    {
      "day": 351,
      "value": 1.87
    },
    {
      "day": 352,
      "value": 1.8599999999999999
    },
    {
      "day": 353,
      "value": 1.8499999999999999
    },
    {
      "day": 354,
      "value": 1.8399999999999999
    },
    {
      "day": 355,
      "value": 1.83
    },
    {
      "day": 356,
      "value": 1.82
    },
    {
      "day": 357,
      "value": 1.81
    },
    {
      "day": 358,
      "value": 1.7999999999999998
    },
    {
      "day": 359,
      "value": 1.79
    },
    {
      "day": 360,
      "value": 1.78
    },
    {
      "day": 361,
      "value": 1.77
    },
    {
      "day": 362,
      "value": 1.76
    },
    {
      "day": 363,
      "value": 1.7500000000000002
    },
    {
      "day": 364,
      "value": 1.7399999999999998
    },
    {
      "day": 365,
      "value": 1.73
    },
    {
      "day": 366,
      "value": 1.72
    },
    {
      "day": 367,
      "value": 1.71
    },
    {
      "day": 368,
      "value": 1.7000000000000002
    },
    {
      "day": 369,
      "value": 1.69
    },
    {
      "day": 370,
      "value": 1.68
    },
    {
      "day": 371,
      "value": 1.68
    },
    {
      "day": 372,
      "value": 1.67
    },
    {
      "day": 373,
      "value": 1.66
    },
    {
      "day": 374,
      "value": 1.6500000000000001
    },
    {
      "day": 375,
      "value": 1.6400000000000001
    },
    {
      "day": 376,
      "value": 1.63
    },
    {
      "day": 377,
      "value": 1.6199999999999999
    },
    {
      "day": 378,
      "value": 1.6099999999999999
    },
    {
      "day": 379,
      "value": 1.6099999999999999
    },
    {
      "day": 380,
      "value": 1.6
    },
    {
      "day": 381,
      "value": 1.59
    },
    {
      "day": 382,
      "value": 1.58
    },
    {
      "day": 383,
      "value": 1.5699999999999998
    },
    {
      "day": 384,
      "value": 1.5699999999999998
    },
    {
      "day": 385,
      "value": 1.5599999999999998
    },
    {
      "day": 386,
      "value": 1.55
    },
    {
      "day": 387,
      "value": 1.54
    },
    {
      "day": 388,
      "value": 1.53
    },
    {
      "day": 389,
      "value": 1.53
    },
    {
      "day": 390,
      "value": 1.52
    },
    {
      "day": 391,
      "value": 1.51
    },
    {
      "day": 392,
      "value": 1.5
    },
    {
      "day": 393,
      "value": 1.5
    },
    {
      "day": 394,
      "value": 1.49
    },
    {
      "day": 395,
      "value": 1.48
    },
    {
      "day": 396,
      "value": 1.47
    },
    {
      "day": 397,
      "value": 1.47
    },
    {
      "day": 398,
      "value": 1.46
    },
    {
      "day": 399,
      "value": 1.4500000000000002
    },
    {
      "day": 400,
      "value": 1.44
    },
    {
      "day": 401,
      "value": 1.44
    },
    {
      "day": 402,
      "value": 1.43
    },
    {
      "day": 403,
      "value": 1.4200000000000002
    },
    {
      "day": 404,
      "value": 1.4200000000000002
    },
    {
      "day": 405,
      "value": 1.41
    },
    {
      "day": 406,
      "value": 1.4000000000000001
    },
    {
      "day": 407,
      "value": 1.4000000000000001
    },
    {
      "day": 408,
      "value": 1.39
    },
    {
      "day": 409,
      "value": 1.38
    },
    {
      "day": 410,
      "value": 1.38
    },
    {
      "day": 411,
      "value": 1.37
    },
    {
      "day": 412,
      "value": 1.3599999999999999
    },
    {
      "day": 413,
      "value": 1.3599999999999999
    },
    {
      "day": 414,
      "value": 1.35
    },
    {
      "day": 415,
      "value": 1.34
    },
    {
      "day": 416,
      "value": 1.34
    },
    {
      "day": 417,
      "value": 1.3299999999999998
    },
    {
      "day": 418,
      "value": 1.32
    },
    {
      "day": 419,
      "value": 1.32
    },
    {
      "day": 420,
      "value": 1.31
    },
    {
      "day": 421,
      "value": 1.31
    },
    {
      "day": 422,
      "value": 1.3
    },
    {
      "day": 423,
      "value": 1.29
    },
    {
      "day": 424,
      "value": 1.29
    },
    {
      "day": 425,
      "value": 1.28
    },
    {
      "day": 426,
      "value": 1.28
    },
    {
      "day": 427,
      "value": 1.27
    },
    {
      "day": 428,
      "value": 1.26
    },
    {
      "day": 429,
      "value": 1.26
    },
    {
      "day": 430,
      "value": 1.25
    },
    {
      "day": 431,
      "value": 1.25
    },
    {
      "day": 432,
      "value": 1.24
    },
    {
      "day": 433,
      "value": 1.24
    },
    {
      "day": 434,
      "value": 1.23
    },
    {
      "day": 435,
      "value": 1.22
    },
    {
      "day": 436,
      "value": 1.22
    },
    {
      "day": 437,
      "value": 1.21
    },
    {
      "day": 438,
      "value": 1.21
    },
    {
      "day": 439,
      "value": 1.2
    },
    {
      "day": 440,
      "value": 1.2
    },
    {
      "day": 441,
      "value": 1.1900000000000002
    },
    {
      "day": 442,
      "value": 1.1900000000000002
    },
    {
      "day": 443,
      "value": 1.18
    },
    {
      "day": 444,
      "value": 1.18
    },
    {
      "day": 445,
      "value": 1.17
    },
    {
      "day": 446,
      "value": 1.17
    },
    {
      "day": 447,
      "value": 1.16
    },
    {
      "day": 448,
      "value": 1.16
    },
    {
      "day": 449,
      "value": 1.15
    },
    {
      "day": 450,
      "value": 1.15
    },
    {
      "day": 451,
      "value": 1.1400000000000001
    },
    {
      "day": 452,
      "value": 1.1400000000000001
    },
    {
      "day": 453,
      "value": 1.13
    },
    {
      "day": 454,
      "value": 1.13
    },
    {
      "day": 455,
      "value": 1.1199999999999999
    },
    {
      "day": 456,
      "value": 1.1199999999999999
    },
    {
      "day": 457,
      "value": 1.11
    },
    {
      "day": 458,
      "value": 1.11
    },
    {
      "day": 459,
      "value": 1.0999999999999999
    },
    {
      "day": 460,
      "value": 1.0999999999999999
    },
    {
      "day": 461,
      "value": 1.0999999999999999
    },
    {
      "day": 462,
      "value": 1.09
    },
    {
      "day": 463,
      "value": 1.09
    },
    {
      "day": 464,
      "value": 1.08
    },
    {
      "day": 465,
      "value": 1.08
    },
    {
      "day": 466,
      "value": 1.0699999999999998
    },
    {
      "day": 467,
      "value": 1.0699999999999998
    },
    {
      "day": 468,
      "value": 1.06
    },
    {
      "day": 469,
      "value": 1.06
    },
    {
      "day": 470,
      "value": 1.06
    },
    {
      "day": 471,
      "value": 1.05
    },
    {
      "day": 472,
      "value": 1.05
    },
    {
      "day": 473,
      "value": 1.04
    },
    {
      "day": 474,
      "value": 1.04
    },
    {
      "day": 475,
      "value": 1.04
    },
    {
      "day": 476,
      "value": 1.03
    },
    {
      "day": 477,
      "value": 1.03
    },
    {
      "day": 478,
      "value": 1.02
    },
    {
      "day": 479,
      "value": 1.02
    },
    {
      "day": 480,
      "value": 1.02
    },
    {
      "day": 481,
      "value": 1.01
    },
    {
      "day": 482,
      "value": 1.01
    },
    {
      "day": 483,
      "value": 1
    },
    {
      "day": 484,
      "value": 1
    },
    {
      "day": 485,
      "value": 1
    },
    {
      "day": 486,
      "value": 0.9900000000000001
    },
    {
      "day": 487,
      "value": 0.9900000000000001
    },
    {
      "day": 488,
      "value": 0.9900000000000001
    },
    {
      "day": 489,
      "value": 0.98
    },
    {
      "day": 490,
      "value": 0.98
    },
    {
      "day": 491,
      "value": 0.97
    },
    {
      "day": 492,
      "value": 0.97
    },
    {
      "day": 493,
      "value": 0.97
    },
    {
      "day": 494,
      "value": 0.96
    },
    {
      "day": 495,
      "value": 0.96
    },
    {
      "day": 496,
      "value": 0.96
    },
    {
      "day": 497,
      "value": 0.95
    },
    {
      "day": 498,
      "value": 0.95
    },
    {
      "day": 499,
      "value": 0.95
    },
    {
      "day": 500,
      "value": 0.9400000000000001
    },
    {
      "day": 501,
      "value": 0.9400000000000001
    },
    {
      "day": 502,
      "value": 0.9400000000000001
    },
    {
      "day": 503,
      "value": 0.9299999999999999
    },
    {
      "day": 504,
      "value": 0.9299999999999999
    },
    {
      "day": 505,
      "value": 0.9299999999999999
    },
    {
      "day": 506,
      "value": 0.9199999999999999
    },
    {
      "day": 507,
      "value": 0.9199999999999999
    },
    {
      "day": 508,
      "value": 0.9199999999999999
    },
    {
      "day": 509,
      "value": 0.91
    },
    {
      "day": 510,
      "value": 0.91
    },
    {
      "day": 511,
      "value": 0.91
    },
    {
      "day": 512,
      "value": 0.8999999999999999
    },
    {
      "day": 513,
      "value": 0.8999999999999999
    },
    {
      "day": 514,
      "value": 0.8999999999999999
    },
    {
      "day": 515,
      "value": 0.8999999999999999
    },
    {
      "day": 516,
      "value": 0.89
    },
    {
      "day": 517,
      "value": 0.89
    },
    {
      "day": 518,
      "value": 0.89
    },
    {
      "day": 519,
      "value": 0.88
    },
    {
      "day": 520,
      "value": 0.88
    },
    {
      "day": 521,
      "value": 0.88
    },
    {
      "day": 522,
      "value": 0.88
    },
    {
      "day": 523,
      "value": 0.8699999999999999
    },
    {
      "day": 524,
      "value": 0.8699999999999999
    },
    {
      "day": 525,
      "value": 0.8699999999999999
    },
    {
      "day": 526,
      "value": 0.86
    },
    {
      "day": 527,
      "value": 0.86
    },
    {
      "day": 528,
      "value": 0.86
    },
    {
      "day": 529,
      "value": 0.86
    },
    {
      "day": 530,
      "value": 0.8500000000000001
    },
    {
      "day": 531,
      "value": 0.8500000000000001
    },
    {
      "day": 532,
      "value": 0.8500000000000001
    },
    {
      "day": 533,
      "value": 0.8500000000000001
    },
    {
      "day": 534,
      "value": 0.84
    },
    {
      "day": 535,
      "value": 0.84
    },
    {
      "day": 536,
      "value": 0.84
    },
    {
      "day": 537,
      "value": 0.83
    },
    {
      "day": 538,
      "value": 0.83
    },
    {
      "day": 539,
      "value": 0.83
    },
    {
      "day": 540,
      "value": 0.83
    },
    {
      "day": 541,
      "value": 0.8200000000000001
    },
    {
      "day": 542,
      "value": 0.8200000000000001
    },
    {
      "day": 543,
      "value": 0.8200000000000001
    },
    {
      "day": 544,
      "value": 0.8200000000000001
    },
    {
      "day": 545,
      "value": 0.8200000000000001
    },
    {
      "day": 546,
      "value": 0.8099999999999999
    },
    {
      "day": 547,
      "value": 0.8099999999999999
    },
    {
      "day": 548,
      "value": 0.8099999999999999
    },
    {
      "day": 549,
      "value": 0.8099999999999999
    },
    {
      "day": 550,
      "value": 0.8
    },
    {
      "day": 551,
      "value": 0.8
    },
    {
      "day": 552,
      "value": 0.8
    },
    {
      "day": 553,
      "value": 0.8
    },
    {
      "day": 554,
      "value": 0.79
    },
    {
      "day": 555,
      "value": 0.79
    },
    {
      "day": 556,
      "value": 0.79
    },
    {
      "day": 557,
      "value": 0.79
    },
    {
      "day": 558,
      "value": 0.79
    },
    {
      "day": 559,
      "value": 0.7799999999999999
    },
    {
      "day": 560,
      "value": 0.7799999999999999
    },
    {
      "day": 561,
      "value": 0.7799999999999999
    },
    {
      "day": 562,
      "value": 0.7799999999999999
    },
    {
      "day": 563,
      "value": 0.7799999999999999
    },
    {
      "day": 564,
      "value": 0.77
    },
    {
      "day": 565,
      "value": 0.77
    },
    {
      "day": 566,
      "value": 0.77
    },
    {
      "day": 567,
      "value": 0.77
    },
    {
      "day": 568,
      "value": 0.76
    },
    {
      "day": 569,
      "value": 0.76
    },
    {
      "day": 570,
      "value": 0.76
    },
    {
      "day": 571,
      "value": 0.76
    },
    {
      "day": 572,
      "value": 0.76
    },
    {
      "day": 573,
      "value": 0.76
    },
    {
      "day": 574,
      "value": 0.75
    },
    {
      "day": 575,
      "value": 0.75
    },
    {
      "day": 576,
      "value": 0.75
    },
    {
      "day": 577,
      "value": 0.75
    },
    {
      "day": 578,
      "value": 0.75
    },
    {
      "day": 579,
      "value": 0.74
    },
    {
      "day": 580,
      "value": 0.74
    },
    {
      "day": 581,
      "value": 0.74
    },
    {
      "day": 582,
      "value": 0.74
    },
    {
      "day": 583,
      "value": 0.74
    },
    {
      "day": 584,
      "value": 0.73
    },
    {
      "day": 585,
      "value": 0.73
    },
    {
      "day": 586,
      "value": 0.73
    },
    {
      "day": 587,
      "value": 0.73
    },
    {
      "day": 588,
      "value": 0.73
    },
    {
      "day": 589,
      "value": 0.73
    },
    {
      "day": 590,
      "value": 0.72
    },
    {
      "day": 591,
      "value": 0.72
    },
    {
      "day": 592,
      "value": 0.72
    },
    {
      "day": 593,
      "value": 0.72
    },
    {
      "day": 594,
      "value": 0.72
    },
    {
      "day": 595,
      "value": 0.72
    },
    {
      "day": 596,
      "value": 0.7100000000000001
    },
    {
      "day": 597,
      "value": 0.7100000000000001
    },
    {
      "day": 598,
      "value": 0.7100000000000001
    },
    {
      "day": 599,
      "value": 0.7100000000000001
    },
    {
      "day": 600,
      "value": 0.7100000000000001
    },
    {
      "day": 601,
      "value": 0.7100000000000001
    },
    {
      "day": 602,
      "value": 0.7000000000000001
    },
    {
      "day": 603,
      "value": 0.7000000000000001
    },
    {
      "day": 604,
      "value": 0.7000000000000001
    },
    {
      "day": 605,
      "value": 0.7000000000000001
    },
    {
      "day": 606,
      "value": 0.7000000000000001
    },
    {
      "day": 607,
      "value": 0.7000000000000001
    },
    {
      "day": 608,
      "value": 0.7000000000000001
    },
    {
      "day": 609,
      "value": 0.69
    },
    {
      "day": 610,
      "value": 0.69
    },
    {
      "day": 611,
      "value": 0.69
    },
    {
      "day": 612,
      "value": 0.69
    },
    {
      "day": 613,
      "value": 0.69
    },
    {
      "day": 614,
      "value": 0.69
    },
    {
      "day": 615,
      "value": 0.69
    },
    {
      "day": 616,
      "value": 0.6799999999999999
    },
    {
      "day": 617,
      "value": 0.6799999999999999
    },
    {
      "day": 618,
      "value": 0.6799999999999999
    },
    {
      "day": 619,
      "value": 0.6799999999999999
    },
    {
      "day": 620,
      "value": 0.6799999999999999
    },
    {
      "day": 621,
      "value": 0.6799999999999999
    },
    {
      "day": 622,
      "value": 0.6799999999999999
    },
    {
      "day": 623,
      "value": 0.67
    },
    {
      "day": 624,
      "value": 0.67
    },
    {
      "day": 625,
      "value": 0.67
    },
    {
      "day": 626,
      "value": 0.67
    },
    {
      "day": 627,
      "value": 0.67
    },
    {
      "day": 628,
      "value": 0.67
    },
    {
      "day": 629,
      "value": 0.67
    },
    {
      "day": 630,
      "value": 0.67
    },
    {
      "day": 631,
      "value": 0.66
    },
    {
      "day": 632,
      "value": 0.66
    },
    {
      "day": 633,
      "value": 0.66
    },
    {
      "day": 634,
      "value": 0.66
    },
    {
      "day": 635,
      "value": 0.66
    },
    {
      "day": 636,
      "value": 0.66
    },
    {
      "day": 637,
      "value": 0.66
    },
    {
      "day": 638,
      "value": 0.66
    },
    {
      "day": 639,
      "value": 0.65
    },
    {
      "day": 640,
      "value": 0.65
    },
    {
      "day": 641,
      "value": 0.65
    },
    {
      "day": 642,
      "value": 0.65
    },
    {
      "day": 643,
      "value": 0.65
    },
    {
      "day": 644,
      "value": 0.65
    },
    {
      "day": 645,
      "value": 0.65
    },
    {
      "day": 646,
      "value": 0.65
    },
    {
      "day": 647,
      "value": 0.65
    },
    {
      "day": 648,
      "value": 0.64
    },
    {
      "day": 649,
      "value": 0.64
    },
    {
      "day": 650,
      "value": 0.64
    },
    {
      "day": 651,
      "value": 0.64
    },
    {
      "day": 652,
      "value": 0.64
    },
    {
      "day": 653,
      "value": 0.64
    },
    {
      "day": 654,
      "value": 0.64
    },
    {
      "day": 655,
      "value": 0.64
    },
    {
      "day": 656,
      "value": 0.64
    },
    {
      "day": 657,
      "value": 0.64
    },
    {
      "day": 658,
      "value": 0.63
    },
    {
      "day": 659,
      "value": 0.63
    },
    {
      "day": 660,
      "value": 0.63
    },
    {
      "day": 661,
      "value": 0.63
    },
    {
      "day": 662,
      "value": 0.63
    },
    {
      "day": 663,
      "value": 0.63
    },
    {
      "day": 664,
      "value": 0.63
    },
    {
      "day": 665,
      "value": 0.63
    },
    {
      "day": 666,
      "value": 0.63
    },
    {
      "day": 667,
      "value": 0.63
    },
    {
      "day": 668,
      "value": 0.62
    },
    {
      "day": 669,
      "value": 0.62
    },
    {
      "day": 670,
      "value": 0.62
    },
    {
      "day": 671,
      "value": 0.62
    },
    {
      "day": 672,
      "value": 0.62
    },
    {
      "day": 673,
      "value": 0.62
    },
    {
      "day": 674,
      "value": 0.62
    },
    {
      "day": 675,
      "value": 0.62
    },
    {
      "day": 676,
      "value": 0.62
    },
    {
      "day": 677,
      "value": 0.62
    },
    {
      "day": 678,
      "value": 0.62
    },
    {
      "day": 679,
      "value": 0.61
    },
    {
      "day": 680,
      "value": 0.61
    },
    {
      "day": 681,
      "value": 0.61
    },
    {
      "day": 682,
      "value": 0.61
    },
    {
      "day": 683,
      "value": 0.61
    },
    {
      "day": 684,
      "value": 0.61
    },
    {
      "day": 685,
      "value": 0.61
    },
    {
      "day": 686,
      "value": 0.61
    },
    {
      "day": 687,
      "value": 0.61
    },
    {
      "day": 688,
      "value": 0.61
    },
    {
      "day": 689,
      "value": 0.61
    },
    {
      "day": 690,
      "value": 0.61
    },
    {
      "day": 691,
      "value": 0.6
    },
    {
      "day": 692,
      "value": 0.6
    },
    {
      "day": 693,
      "value": 0.6
    },
    {
      "day": 694,
      "value": 0.6
    },
    {
      "day": 695,
      "value": 0.6
    },
    {
      "day": 696,
      "value": 0.6
    },
    {
      "day": 697,
      "value": 0.6
    },
    {
      "day": 698,
      "value": 0.6
    },
    {
      "day": 699,
      "value": 0.6
    },
    {
      "day": 700,
      "value": 0.6
    },
    {
      "day": 701,
      "value": 0.6
    },
    {
      "day": 702,
      "value": 0.6
    },
    {
      "day": 703,
      "value": 0.6
    },
    {
      "day": 704,
      "value": 0.59
    },
    {
      "day": 705,
      "value": 0.59
    },
    {
      "day": 706,
      "value": 0.59
    },
    {
      "day": 707,
      "value": 0.59
    },
    {
      "day": 708,
      "value": 0.59
    },
    {
      "day": 709,
      "value": 0.59
    },
    {
      "day": 710,
      "value": 0.59
    },
    {
      "day": 711,
      "value": 0.59
    },
    {
      "day": 712,
      "value": 0.59
    },
    {
      "day": 713,
      "value": 0.59
    },
    {
      "day": 714,
      "value": 0.59
    },
    {
      "day": 715,
      "value": 0.59
    },
    {
      "day": 716,
      "value": 0.59
    },
    {
      "day": 717,
      "value": 0.59
    },
    {
      "day": 718,
      "value": 0.59
    },
    {
      "day": 719,
      "value": 0.58
    },
    {
      "day": 720,
      "value": 0.58
    },
    {
      "day": 721,
      "value": 0.58
    },
    {
      "day": 722,
      "value": 0.58
    },
    {
      "day": 723,
      "value": 0.58
    },
    {
      "day": 724,
      "value": 0.58
    },
    {
      "day": 725,
      "value": 0.58
    },
    {
      "day": 726,
      "value": 0.58
    },
    {
      "day": 727,
      "value": 0.58
    },
    {
      "day": 728,
      "value": 0.58
    },
    {
      "day": 729,
      "value": 0.58
    },
    {
      "day": 730,
      "value": 0.58
    },
    {
      "day": 731,
      "value": 0.58
    },
    {
      "day": 732,
      "value": 0.58
    },
    {
      "day": 733,
      "value": 0.58
    },
    {
      "day": 734,
      "value": 0.58
    },
    {
      "day": 735,
      "value": 0.5700000000000001
    },
    {
      "day": 736,
      "value": 0.5700000000000001
    },
    {
      "day": 737,
      "value": 0.5700000000000001
    },
    {
      "day": 738,
      "value": 0.5700000000000001
    },
    {
      "day": 739,
      "value": 0.5700000000000001
    },
    {
      "day": 740,
      "value": 0.5700000000000001
    },
    {
      "day": 741,
      "value": 0.5700000000000001
    },
    {
      "day": 742,
      "value": 0.5700000000000001
    },
    {
      "day": 743,
      "value": 0.5700000000000001
    },
    {
      "day": 744,
      "value": 0.5700000000000001
    },
    {
      "day": 745,
      "value": 0.5700000000000001
    },
    {
      "day": 746,
      "value": 0.5700000000000001
    },
    {
      "day": 747,
      "value": 0.5700000000000001
    },
    {
      "day": 748,
      "value": 0.5700000000000001
    },
    {
      "day": 749,
      "value": 0.5700000000000001
    },
    {
      "day": 750,
      "value": 0.5700000000000001
    },
    {
      "day": 751,
      "value": 0.5700000000000001
    },
    {
      "day": 752,
      "value": 0.5700000000000001
    },
    {
      "day": 753,
      "value": 0.5700000000000001
    },
    {
      "day": 754,
      "value": 0.5599999999999999
    },
    {
      "day": 755,
      "value": 0.5599999999999999
    },
    {
      "day": 756,
      "value": 0.5599999999999999
    },
    {
      "day": 757,
      "value": 0.5599999999999999
    },
    {
      "day": 758,
      "value": 0.5599999999999999
    },
    {
      "day": 759,
      "value": 0.5599999999999999
    },
    {
      "day": 760,
      "value": 0.5599999999999999
    },
    {
      "day": 761,
      "value": 0.5599999999999999
    },
    {
      "day": 762,
      "value": 0.5599999999999999
    },
    {
      "day": 763,
      "value": 0.5599999999999999
    },
    {
      "day": 764,
      "value": 0.5599999999999999
    },
    {
      "day": 765,
      "value": 0.5599999999999999
    },
    {
      "day": 766,
      "value": 0.5599999999999999
    },
    {
      "day": 767,
      "value": 0.5599999999999999
    },
    {
      "day": 768,
      "value": 0.5599999999999999
    },
    {
      "day": 769,
      "value": 0.5599999999999999
    },
    {
      "day": 770,
      "value": 0.5599999999999999
    },
    {
      "day": 771,
      "value": 0.5599999999999999
    },
    {
      "day": 772,
      "value": 0.5599999999999999
    },
    {
      "day": 773,
      "value": 0.5599999999999999
    },
    {
      "day": 774,
      "value": 0.5599999999999999
    },
    {
      "day": 775,
      "value": 0.5599999999999999
    },
    {
      "day": 776,
      "value": 0.5499999999999999
    },
    {
      "day": 777,
      "value": 0.5499999999999999
    },
    {
      "day": 778,
      "value": 0.5499999999999999
    },
    {
      "day": 779,
      "value": 0.5499999999999999
    },
    {
      "day": 780,
      "value": 0.5499999999999999
    },
    {
      "day": 781,
      "value": 0.5499999999999999
    },
    {
      "day": 782,
      "value": 0.5499999999999999
    },
    {
      "day": 783,
      "value": 0.5499999999999999
    },
    {
      "day": 784,
      "value": 0.5499999999999999
    },
    {
      "day": 785,
      "value": 0.5499999999999999
    },
    {
      "day": 786,
      "value": 0.5499999999999999
    },
    {
      "day": 787,
      "value": 0.5499999999999999
    },
    {
      "day": 788,
      "value": 0.5499999999999999
    },
    {
      "day": 789,
      "value": 0.5499999999999999
    },
    {
      "day": 790,
      "value": 0.5499999999999999
    },
    {
      "day": 791,
      "value": 0.5499999999999999
    },
    {
      "day": 792,
      "value": 0.5499999999999999
    },
    {
      "day": 793,
      "value": 0.5499999999999999
    },
    {
      "day": 794,
      "value": 0.5499999999999999
    },
    {
      "day": 795,
      "value": 0.5499999999999999
    },
    {
      "day": 796,
      "value": 0.5499999999999999
    },
    {
      "day": 797,
      "value": 0.5499999999999999
    },
    {
      "day": 798,
      "value": 0.5499999999999999
    },
    {
      "day": 799,
      "value": 0.5499999999999999
    },
    {
      "day": 800,
      "value": 0.5499999999999999
    },
    {
      "day": 801,
      "value": 0.5499999999999999
    },
    {
      "day": 802,
      "value": 0.5499999999999999
    },
    {
      "day": 803,
      "value": 0.54
    },
    {
      "day": 804,
      "value": 0.54
    },
    {
      "day": 805,
      "value": 0.54
    },
    {
      "day": 806,
      "value": 0.54
    },
    {
      "day": 807,
      "value": 0.54
    },
    {
      "day": 808,
      "value": 0.54
    },
    {
      "day": 809,
      "value": 0.54
    },
    {
      "day": 810,
      "value": 0.54
    },
    {
      "day": 811,
      "value": 0.54
    },
    {
      "day": 812,
      "value": 0.54
    },
    {
      "day": 813,
      "value": 0.54
    },
    {
      "day": 814,
      "value": 0.54
    },
    {
      "day": 815,
      "value": 0.54
    },
    {
      "day": 816,
      "value": 0.54
    },
    {
      "day": 817,
      "value": 0.54
    },
    {
      "day": 818,
      "value": 0.54
    },
    {
      "day": 819,
      "value": 0.54
    },
    {
      "day": 820,
      "value": 0.54
    },
    {
      "day": 821,
      "value": 0.54
    },
    {
      "day": 822,
      "value": 0.54
    },
    {
      "day": 823,
      "value": 0.54
    },
    {
      "day": 824,
      "value": 0.54
    },
    {
      "day": 825,
      "value": 0.54
    },
    {
      "day": 826,
      "value": 0.54
    },
    {
      "day": 827,
      "value": 0.54
    },
    {
      "day": 828,
      "value": 0.54
    },
    {
      "day": 829,
      "value": 0.54
    },
    {
      "day": 830,
      "value": 0.54
    },
    {
      "day": 831,
      "value": 0.54
    },
    {
      "day": 832,
      "value": 0.54
    },
    {
      "day": 833,
      "value": 0.54
    },
    {
      "day": 834,
      "value": 0.54
    },
    {
      "day": 835,
      "value": 0.54
    },
    {
      "day": 836,
      "value": 0.53
    },
    {
      "day": 837,
      "value": 0.53
    },
    {
      "day": 838,
      "value": 0.53
    },
    {
      "day": 839,
      "value": 0.53
    },
    {
      "day": 840,
      "value": 0.53
    },
    {
      "day": 841,
      "value": 0.53
    },
    {
      "day": 842,
      "value": 0.53
    },
    {
      "day": 843,
      "value": 0.53
    },
    {
      "day": 844,
      "value": 0.53
    },
    {
      "day": 845,
      "value": 0.53
    },
    {
      "day": 846,
      "value": 0.53
    },
    {
      "day": 847,
      "value": 0.53
    },
    {
      "day": 848,
      "value": 0.53
    },
    {
      "day": 849,
      "value": 0.53
    },
    {
      "day": 850,
      "value": 0.53
    },
    {
      "day": 851,
      "value": 0.53
    },
    {
      "day": 852,
      "value": 0.53
    },
    {
      "day": 853,
      "value": 0.53
    },
    {
      "day": 854,
      "value": 0.53
    },
    {
      "day": 855,
      "value": 0.53
    },
    {
      "day": 856,
      "value": 0.53
    },
    {
      "day": 857,
      "value": 0.53
    },
    {
      "day": 858,
      "value": 0.53
    },
    {
      "day": 859,
      "value": 0.53
    },
    {
      "day": 860,
      "value": 0.53
    },
    {
      "day": 861,
      "value": 0.53
    },
    {
      "day": 862,
      "value": 0.53
    },
    {
      "day": 863,
      "value": 0.53
    },
    {
      "day": 864,
      "value": 0.53
    },
    {
      "day": 865,
      "value": 0.53
    },
    {
      "day": 866,
      "value": 0.53
    },
    {
      "day": 867,
      "value": 0.53
    },
    {
      "day": 868,
      "value": 0.53
    },
    {
      "day": 869,
      "value": 0.53
    },
    {
      "day": 870,
      "value": 0.53
    },
    {
      "day": 871,
      "value": 0.53
    },
    {
      "day": 872,
      "value": 0.53
    },
    {
      "day": 873,
      "value": 0.53
    },
    {
      "day": 874,
      "value": 0.53
    },
    {
      "day": 875,
      "value": 0.53
    },
    {
      "day": 876,
      "value": 0.53
    },
    {
      "day": 877,
      "value": 0.53
    },
    {
      "day": 878,
      "value": 0.53
    },
    {
      "day": 879,
      "value": 0.53
    },
    {
      "day": 880,
      "value": 0.53
    },
    {
      "day": 881,
      "value": 0.52
    },
    {
      "day": 882,
      "value": 0.52
    },
    {
      "day": 883,
      "value": 0.52
    },
    {
      "day": 884,
      "value": 0.52
    },
    {
      "day": 885,
      "value": 0.52
    },
    {
      "day": 886,
      "value": 0.52
    },
    {
      "day": 887,
      "value": 0.52
    },
    {
      "day": 888,
      "value": 0.52
    },
    {
      "day": 889,
      "value": 0.52
    },
    {
      "day": 890,
      "value": 0.52
    },
    {
      "day": 891,
      "value": 0.52
    },
    {
      "day": 892,
      "value": 0.52
    },
    {
      "day": 893,
      "value": 0.52
    },
    {
      "day": 894,
      "value": 0.52
    },
    {
      "day": 895,
      "value": 0.52
    },
    {
      "day": 896,
      "value": 0.52
    },
    {
      "day": 897,
      "value": 0.52
    },
    {
      "day": 898,
      "value": 0.52
    },
    {
      "day": 899,
      "value": 0.52
    },
    {
      "day": 900,
      "value": 0.52
    },
    {
      "day": 901,
      "value": 0.52
    },
    {
      "day": 902,
      "value": 0.52
    },
    {
      "day": 903,
      "value": 0.52
    },
    {
      "day": 904,
      "value": 0.52
    },
    {
      "day": 905,
      "value": 0.52
    },
    {
      "day": 906,
      "value": 0.52
    },
    {
      "day": 907,
      "value": 0.52
    },
    {
      "day": 908,
      "value": 0.52
    },
    {
      "day": 909,
      "value": 0.52
    },
    {
      "day": 910,
      "value": 0.52
    },
    {
      "day": 911,
      "value": 0.52
    },
    {
      "day": 912,
      "value": 0.52
    },
    {
      "day": 913,
      "value": 0.52
    },
    {
      "day": 914,
      "value": 0.52
    },
    {
      "day": 915,
      "value": 0.52
    },
    {
      "day": 916,
      "value": 0.52
    },
    {
      "day": 917,
      "value": 0.52
    },
    {
      "day": 918,
      "value": 0.52
    },
    {
      "day": 919,
      "value": 0.52
    },
    {
      "day": 920,
      "value": 0.52
    },
    {
      "day": 921,
      "value": 0.52
    },
    {
      "day": 922,
      "value": 0.52
    },
    {
      "day": 923,
      "value": 0.52
    },
    {
      "day": 924,
      "value": 0.52
    },
    {
      "day": 925,
      "value": 0.52
    },
    {
      "day": 926,
      "value": 0.52
    },
    {
      "day": 927,
      "value": 0.52
    },
    {
      "day": 928,
      "value": 0.52
    },
    {
      "day": 929,
      "value": 0.52
    },
    {
      "day": 930,
      "value": 0.52
    },
    {
      "day": 931,
      "value": 0.52
    },
    {
      "day": 932,
      "value": 0.52
    },
    {
      "day": 933,
      "value": 0.52
    },
    {
      "day": 934,
      "value": 0.52
    },
    {
      "day": 935,
      "value": 0.52
    },
    {
      "day": 936,
      "value": 0.52
    },
    {
      "day": 937,
      "value": 0.52
    },
    {
      "day": 938,
      "value": 0.52
    },
    {
      "day": 939,
      "value": 0.52
    },
    {
      "day": 940,
      "value": 0.52
    },
    {
      "day": 941,
      "value": 0.52
    },
    {
      "day": 942,
      "value": 0.52
    },
    {
      "day": 943,
      "value": 0.52
    },
    {
      "day": 944,
      "value": 0.52
    },
    {
      "day": 945,
      "value": 0.52
    },
    {
      "day": 946,
      "value": 0.52
    },
    {
      "day": 947,
      "value": 0.52
    },
    {
      "day": 948,
      "value": 0.51
    },
    {
      "day": 949,
      "value": 0.51
    },
    {
      "day": 950,
      "value": 0.51
    },
    {
      "day": 951,
      "value": 0.51
    },
    {
      "day": 952,
      "value": 0.51
    },
    {
      "day": 953,
      "value": 0.51
    },
    {
      "day": 954,
      "value": 0.51
    },
    {
      "day": 955,
      "value": 0.51
    },
    {
      "day": 956,
      "value": 0.51
    },
    {
      "day": 957,
      "value": 0.51
    },
    {
      "day": 958,
      "value": 0.51
    },
    {
      "day": 959,
      "value": 0.51
    },
    {
      "day": 960,
      "value": 0.51
    },
    {
      "day": 961,
      "value": 0.51
    },
    {
      "day": 962,
      "value": 0.51
    },
    {
      "day": 963,
      "value": 0.51
    },
    {
      "day": 964,
      "value": 0.51
    },
    {
      "day": 965,
      "value": 0.51
    },
    {
      "day": 966,
      "value": 0.51
    },
    {
      "day": 967,
      "value": 0.51
    },
    {
      "day": 968,
      "value": 0.51
    },
    {
      "day": 969,
      "value": 0.51
    },
    {
      "day": 970,
      "value": 0.51
    },
    {
      "day": 971,
      "value": 0.51
    },
    {
      "day": 972,
      "value": 0.51
    },
    {
      "day": 973,
      "value": 0.51
    },
    {
      "day": 974,
      "value": 0.51
    },
    {
      "day": 975,
      "value": 0.51
    },
    {
      "day": 976,
      "value": 0.51
    },
    {
      "day": 977,
      "value": 0.51
    },
    {
      "day": 978,
      "value": 0.51
    },
    {
      "day": 979,
      "value": 0.51
    },
    {
      "day": 980,
      "value": 0.51
    },
    {
      "day": 981,
      "value": 0.51
    },
    {
      "day": 982,
      "value": 0.51
    },
    {
      "day": 983,
      "value": 0.51
    },
    {
      "day": 984,
      "value": 0.51
    },
    {
      "day": 985,
      "value": 0.51
    },
    {
      "day": 986,
      "value": 0.51
    },
    {
      "day": 987,
      "value": 0.51
    },
    {
      "day": 988,
      "value": 0.51
    },
    {
      "day": 989,
      "value": 0.51
    },
    {
      "day": 990,
      "value": 0.51
    },
    {
      "day": 991,
      "value": 0.51
    },
    {
      "day": 992,
      "value": 0.51
    },
    {
      "day": 993,
      "value": 0.51
    },
    {
      "day": 994,
      "value": 0.51
    },
    {
      "day": 995,
      "value": 0.51
    },
    {
      "day": 996,
      "value": 0.51
    },
    {
      "day": 997,
      "value": 0.51
    },
    {
      "day": 998,
      "value": 0.51
    },
    {
      "day": 999,
      "value": 0.51
    },
    {
      "day": 1000,
      "value": 0.51
    },
    {
      "day": 1001,
      "value": 0.51
    },
    {
      "day": 1002,
      "value": 0.51
    },
    {
      "day": 1003,
      "value": 0.51
    },
    {
      "day": 1004,
      "value": 0.51
    },
    {
      "day": 1005,
      "value": 0.51
    },
    {
      "day": 1006,
      "value": 0.51
    },
    {
      "day": 1007,
      "value": 0.51
    },
    {
      "day": 1008,
      "value": 0.51
    },
    {
      "day": 1009,
      "value": 0.51
    },
    {
      "day": 1010,
      "value": 0.51
    },
    {
      "day": 1011,
      "value": 0.51
    },
    {
      "day": 1012,
      "value": 0.51
    },
    {
      "day": 1013,
      "value": 0.51
    },
    {
      "day": 1014,
      "value": 0.51
    },
    {
      "day": 1015,
      "value": 0.51
    },
    {
      "day": 1016,
      "value": 0.51
    },
    {
      "day": 1017,
      "value": 0.51
    },
    {
      "day": 1018,
      "value": 0.51
    },
    {
      "day": 1019,
      "value": 0.51
    },
    {
      "day": 1020,
      "value": 0.51
    },
    {
      "day": 1021,
      "value": 0.51
    },
    {
      "day": 1022,
      "value": 0.51
    },
    {
      "day": 1023,
      "value": 0.51
    },
    {
      "day": 1024,
      "value": 0.51
    },
    {
      "day": 1025,
      "value": 0.51
    },
    {
      "day": 1026,
      "value": 0.51
    },
    {
      "day": 1027,
      "value": 0.51
    },
    {
      "day": 1028,
      "value": 0.51
    },
    {
      "day": 1029,
      "value": 0.51
    },
    {
      "day": 1030,
      "value": 0.51
    },
    {
      "day": 1031,
      "value": 0.51
    },
    {
      "day": 1032,
      "value": 0.51
    },
    {
      "day": 1033,
      "value": 0.51
    },
    {
      "day": 1034,
      "value": 0.51
    },
    {
      "day": 1035,
      "value": 0.51
    },
    {
      "day": 1036,
      "value": 0.51
    },
    {
      "day": 1037,
      "value": 0.51
    },
    {
      "day": 1038,
      "value": 0.51
    },
    {
      "day": 1039,
      "value": 0.51
    },
    {
      "day": 1040,
      "value": 0.51
    },
    {
      "day": 1041,
      "value": 0.51
    },
    {
      "day": 1042,
      "value": 0.51
    },
    {
      "day": 1043,
      "value": 0.51
    },
    {
      "day": 1044,
      "value": 0.51
    },
    {
      "day": 1045,
      "value": 0.51
    },
    {
      "day": 1046,
      "value": 0.51
    },
    {
      "day": 1047,
      "value": 0.51
    },
    {
      "day": 1048,
      "value": 0.51
    },
    {
      "day": 1049,
      "value": 0.51
    },
    {
      "day": 1050,
      "value": 0.51
    },
    {
      "day": 1051,
      "value": 0.51
    },
    {
      "day": 1052,
      "value": 0.51
    },
    {
      "day": 1053,
      "value": 0.51
    },
    {
      "day": 1054,
      "value": 0.51
    },
    {
      "day": 1055,
      "value": 0.51
    },
    {
      "day": 1056,
      "value": 0.51
    },
    {
      "day": 1057,
      "value": 0.51
    },
    {
      "day": 1058,
      "value": 0.51
    },
    {
      "day": 1059,
      "value": 0.51
    },
    {
      "day": 1060,
      "value": 0.51
    },
    {
      "day": 1061,
      "value": 0.51
    },
    {
      "day": 1062,
      "value": 0.51
    },
    {
      "day": 1063,
      "value": 0.51
    },
    {
      "day": 1064,
      "value": 0.51
    },
    {
      "day": 1065,
      "value": 0.51
    },
    {
      "day": 1066,
      "value": 0.51
    },
    {
      "day": 1067,
      "value": 0.51
    },
    {
      "day": 1068,
      "value": 0.51
    },
    {
      "day": 1069,
      "value": 0.51
    },
    {
      "day": 1070,
      "value": 0.51
    },
    {
      "day": 1071,
      "value": 0.51
    },
    {
      "day": 1072,
      "value": 0.51
    },
    {
      "day": 1073,
      "value": 0.51
    },
    {
      "day": 1074,
      "value": 0.51
    },
    {
      "day": 1075,
      "value": 0.51
    },
    {
      "day": 1076,
      "value": 0.51
    },
    {
      "day": 1077,
      "value": 0.51
    },
    {
      "day": 1078,
      "value": 0.51
    },
    {
      "day": 1079,
      "value": 0.51
    },
    {
      "day": 1080,
      "value": 0.51
    },
    {
      "day": 1081,
      "value": 0.51
    },
    {
      "day": 1082,
      "value": 0.51
    },
    {
      "day": 1083,
      "value": 0.51
    },
    {
      "day": 1084,
      "value": 0.51
    },
    {
      "day": 1085,
      "value": 0.51
    },
    {
      "day": 1086,
      "value": 0.51
    },
    {
      "day": 1087,
      "value": 0.51
    },
    {
      "day": 1088,
      "value": 0.51
    },
    {
      "day": 1089,
      "value": 0.51
    },
    {
      "day": 1090,
      "value": 0.51
    },
    {
      "day": 1091,
      "value": 0.51
    },
    {
      "day": 1092,
      "value": 0.51
    },
    {
      "day": 1093,
      "value": 0.5
    },
    {
      "day": 1094,
      "value": 0.5
    },
    {
      "day": 1095,
      "value": 0.5
    },
    {
      "day": 1096,
      "value": 0.5
    },
    {
      "day": 1097,
      "value": 0.5
    },
    {
      "day": 1098,
      "value": 0.5
    },
    {
      "day": 1099,
      "value": 0.5
    },
    {
      "day": 1100,
      "value": 0.5
    },
    {
      "day": 1101,
      "value": 0.5
    },
    {
      "day": 1102,
      "value": 0.5
    },
    {
      "day": 1103,
      "value": 0.5
    },
    {
      "day": 1104,
      "value": 0.5
    },
    {
      "day": 1105,
      "value": 0.5
    },
    {
      "day": 1106,
      "value": 0.5
    },
    {
      "day": 1107,
      "value": 0.5
    },
    {
      "day": 1108,
      "value": 0.5
    },
    {
      "day": 1109,
      "value": 0.5
    },
    {
      "day": 1110,
      "value": 0.5
    },
    {
      "day": 1111,
      "value": 0.5
    },
    {
      "day": 1112,
      "value": 0.5
    },
    {
      "day": 1113,
      "value": 0.5
    },
    {
      "day": 1114,
      "value": 0.5
    },
    {
      "day": 1115,
      "value": 0.5
    },
    {
      "day": 1116,
      "value": 0.5
    },
    {
      "day": 1117,
      "value": 0.5
    },
    {
      "day": 1118,
      "value": 0.5
    },
    {
      "day": 1119,
      "value": 0.5
    },
    {
      "day": 1120,
      "value": 0.5
    },
    {
      "day": 1121,
      "value": 0.5
    },
    {
      "day": 1122,
      "value": 0.5
    },
    {
      "day": 1123,
      "value": 0.5
    },
    {
      "day": 1124,
      "value": 0.5
    },
    {
      "day": 1125,
      "value": 0.5
    },
    {
      "day": 1126,
      "value": 0.5
    },
    {
      "day": 1127,
      "value": 0.5
    },
    {
      "day": 1128,
      "value": 0.5
    },
    {
      "day": 1129,
      "value": 0.5
    },
    {
      "day": 1130,
      "value": 0.5
    },
    {
      "day": 1131,
      "value": 0.5
    },
    {
      "day": 1132,
      "value": 0.5
    },
    {
      "day": 1133,
      "value": 0.5
    },
    {
      "day": 1134,
      "value": 0.5
    },
    {
      "day": 1135,
      "value": 0.5
    },
    {
      "day": 1136,
      "value": 0.5
    },
    {
      "day": 1137,
      "value": 0.5
    },
    {
      "day": 1138,
      "value": 0.5
    },
    {
      "day": 1139,
      "value": 0.5
    },
    {
      "day": 1140,
      "value": 0.5
    },
    {
      "day": 1141,
      "value": 0.5
    },
    {
      "day": 1142,
      "value": 0.5
    },
    {
      "day": 1143,
      "value": 0.5
    },
    {
      "day": 1144,
      "value": 0.5
    },
    {
      "day": 1145,
      "value": 0.5
    },
    {
      "day": 1146,
      "value": 0.5
    },
    {
      "day": 1147,
      "value": 0.5
    },
    {
      "day": 1148,
      "value": 0.5
    },
    {
      "day": 1149,
      "value": 0.5
    },
    {
      "day": 1150,
      "value": 0.5
    },
    {
      "day": 1151,
      "value": 0.5
    },
    {
      "day": 1152,
      "value": 0.5
    },
    {
      "day": 1153,
      "value": 0.5
    },
    {
      "day": 1154,
      "value": 0.5
    },
    {
      "day": 1155,
      "value": 0.5
    },
    {
      "day": 1156,
      "value": 0.5
    },
    {
      "day": 1157,
      "value": 0.5
    },
    {
      "day": 1158,
      "value": 0.5
    },
    {
      "day": 1159,
      "value": 0.5
    },
    {
      "day": 1160,
      "value": 0.5
    },
    {
      "day": 1161,
      "value": 0.5
    },
    {
      "day": 1162,
      "value": 0.5
    },
    {
      "day": 1163,
      "value": 0.5
    },
    {
      "day": 1164,
      "value": 0.5
    },
    {
      "day": 1165,
      "value": 0.5
    },
    {
      "day": 1166,
      "value": 0.5
    },
    {
      "day": 1167,
      "value": 0.5
    },
    {
      "day": 1168,
      "value": 0.5
    },
    {
      "day": 1169,
      "value": 0.5
    },
    {
      "day": 1170,
      "value": 0.5
    },
    {
      "day": 1171,
      "value": 0.5
    },
    {
      "day": 1172,
      "value": 0.5
    },
    {
      "day": 1173,
      "value": 0.5
    },
    {
      "day": 1174,
      "value": 0.5
    },
    {
      "day": 1175,
      "value": 0.5
    },
    {
      "day": 1176,
      "value": 0.5
    },
    {
      "day": 1177,
      "value": 0.5
    },
    {
      "day": 1178,
      "value": 0.5
    },
    {
      "day": 1179,
      "value": 0.5
    },
    {
      "day": 1180,
      "value": 0.5
    },
    {
      "day": 1181,
      "value": 0.5
    },
    {
      "day": 1182,
      "value": 0.5
    },
    {
      "day": 1183,
      "value": 0.5
    },
    {
      "day": 1184,
      "value": 0.5
    },
    {
      "day": 1185,
      "value": 0.5
    },
    {
      "day": 1186,
      "value": 0.5
    },
    {
      "day": 1187,
      "value": 0.5
    },
    {
      "day": 1188,
      "value": 0.5
    },
    {
      "day": 1189,
      "value": 0.5
    },
    {
      "day": 1190,
      "value": 0.5
    },
    {
      "day": 1191,
      "value": 0.5
    },
    {
      "day": 1192,
      "value": 0.5
    },
    {
      "day": 1193,
      "value": 0.5
    },
    {
      "day": 1194,
      "value": 0.5
    },
    {
      "day": 1195,
      "value": 0.5
    },
    {
      "day": 1196,
      "value": 0.5
    },
    {
      "day": 1197,
      "value": 0.5
    },
    {
      "day": 1198,
      "value": 0.5
    },
    {
      "day": 1199,
      "value": 0.5
    },
    {
      "day": 1200,
      "value": 0.5
    },
    {
      "day": 1201,
      "value": 0.5
    },
    {
      "day": 1202,
      "value": 0.5
    },
    {
      "day": 1203,
      "value": 0.5
    },
    {
      "day": 1204,
      "value": 0.5
    },
    {
      "day": 1205,
      "value": 0.5
    },
    {
      "day": 1206,
      "value": 0.5
    },
    {
      "day": 1207,
      "value": 0.5
    },
    {
      "day": 1208,
      "value": 0.5
    },
    {
      "day": 1209,
      "value": 0.5
    },
    {
      "day": 1210,
      "value": 0.5
    },
    {
      "day": 1211,
      "value": 0.5
    },
    {
      "day": 1212,
      "value": 0.5
    },
    {
      "day": 1213,
      "value": 0.5
    },
    {
      "day": 1214,
      "value": 0.5
    },
    {
      "day": 1215,
      "value": 0.5
    },
    {
      "day": 1216,
      "value": 0.5
    },
    {
      "day": 1217,
      "value": 0.5
    },
    {
      "day": 1218,
      "value": 0.5
    },
    {
      "day": 1219,
      "value": 0.5
    },
    {
      "day": 1220,
      "value": 0.5
    },
    {
      "day": 1221,
      "value": 0.5
    },
    {
      "day": 1222,
      "value": 0.5
    },
    {
      "day": 1223,
      "value": 0.5
    },
    {
      "day": 1224,
      "value": 0.5
    },
    {
      "day": 1225,
      "value": 0.5
    },
    {
      "day": 1226,
      "value": 0.5
    },
    {
      "day": 1227,
      "value": 0.5
    },
    {
      "day": 1228,
      "value": 0.5
    },
    {
      "day": 1229,
      "value": 0.5
    },
    {
      "day": 1230,
      "value": 0.5
    },
    {
      "day": 1231,
      "value": 0.5
    },
    {
      "day": 1232,
      "value": 0.5
    },
    {
      "day": 1233,
      "value": 0.5
    },
    {
      "day": 1234,
      "value": 0.5
    },
    {
      "day": 1235,
      "value": 0.5
    },
    {
      "day": 1236,
      "value": 0.5
    },
    {
      "day": 1237,
      "value": 0.5
    },
    {
      "day": 1238,
      "value": 0.5
    },
    {
      "day": 1239,
      "value": 0.5
    },
    {
      "day": 1240,
      "value": 0.5
    },
    {
      "day": 1241,
      "value": 0.5
    },
    {
      "day": 1242,
      "value": 0.5
    },
    {
      "day": 1243,
      "value": 0.5
    },
    {
      "day": 1244,
      "value": 0.5
    },
    {
      "day": 1245,
      "value": 0.5
    },
    {
      "day": 1246,
      "value": 0.5
    },
    {
      "day": 1247,
      "value": 0.5
    },
    {
      "day": 1248,
      "value": 0.5
    },
    {
      "day": 1249,
      "value": 0.5
    },
    {
      "day": 1250,
      "value": 0.5
    },
    {
      "day": 1251,
      "value": 0.5
    },
    {
      "day": 1252,
      "value": 0.5
    },
    {
      "day": 1253,
      "value": 0.5
    },
    {
      "day": 1254,
      "value": 0.5
    },
    {
      "day": 1255,
      "value": 0.5
    },
    {
      "day": 1256,
      "value": 0.5
    },
    {
      "day": 1257,
      "value": 0.5
    },
    {
      "day": 1258,
      "value": 0.5
    },
    {
      "day": 1259,
      "value": 0.5
    },
    {
      "day": 1260,
      "value": 0.5
    },
    {
      "day": 1261,
      "value": 0.5
    },
    {
      "day": 1262,
      "value": 0.5
    },
    {
      "day": 1263,
      "value": 0.5
    },
    {
      "day": 1264,
      "value": 0.5
    },
    {
      "day": 1265,
      "value": 0.5
    },
    {
      "day": 1266,
      "value": 0.5
    },
    {
      "day": 1267,
      "value": 0.5
    },
    {
      "day": 1268,
      "value": 0.5
    },
    {
      "day": 1269,
      "value": 0.5
    },
    {
      "day": 1270,
      "value": 0.5
    },
    {
      "day": 1271,
      "value": 0.5
    },
    {
      "day": 1272,
      "value": 0.5
    },
    {
      "day": 1273,
      "value": 0.5
    },
    {
      "day": 1274,
      "value": 0.5
    },
    {
      "day": 1275,
      "value": 0.5
    },
    {
      "day": 1276,
      "value": 0.5
    },
    {
      "day": 1277,
      "value": 0.5
    },
    {
      "day": 1278,
      "value": 0.5
    },
    {
      "day": 1279,
      "value": 0.5
    },
    {
      "day": 1280,
      "value": 0.5
    },
    {
      "day": 1281,
      "value": 0.5
    },
    {
      "day": 1282,
      "value": 0.5
    },
    {
      "day": 1283,
      "value": 0.5
    },
    {
      "day": 1284,
      "value": 0.5
    },
    {
      "day": 1285,
      "value": 0.5
    },
    {
      "day": 1286,
      "value": 0.5
    },
    {
      "day": 1287,
      "value": 0.5
    },
    {
      "day": 1288,
      "value": 0.5
    },
    {
      "day": 1289,
      "value": 0.5
    },
    {
      "day": 1290,
      "value": 0.5
    },
    {
      "day": 1291,
      "value": 0.5
    },
    {
      "day": 1292,
      "value": 0.5
    },
    {
      "day": 1293,
      "value": 0.5
    },
    {
      "day": 1294,
      "value": 0.5
    },
    {
      "day": 1295,
      "value": 0.5
    },
    {
      "day": 1296,
      "value": 0.5
    },
    {
      "day": 1297,
      "value": 0.5
    },
    {
      "day": 1298,
      "value": 0.5
    },
    {
      "day": 1299,
      "value": 0.5
    },
    {
      "day": 1300,
      "value": 0.5
    },
    {
      "day": 1301,
      "value": 0.5
    },
    {
      "day": 1302,
      "value": 0.5
    },
    {
      "day": 1303,
      "value": 0.5
    },
    {
      "day": 1304,
      "value": 0.5
    },
    {
      "day": 1305,
      "value": 0.5
    },
    {
      "day": 1306,
      "value": 0.5
    },
    {
      "day": 1307,
      "value": 0.5
    },
    {
      "day": 1308,
      "value": 0.5
    },
    {
      "day": 1309,
      "value": 0.5
    },
    {
      "day": 1310,
      "value": 0.5
    },
    {
      "day": 1311,
      "value": 0.5
    },
    {
      "day": 1312,
      "value": 0.5
    },
    {
      "day": 1313,
      "value": 0.5
    },
    {
      "day": 1314,
      "value": 0.5
    },
    {
      "day": 1315,
      "value": 0.5
    },
    {
      "day": 1316,
      "value": 0.5
    },
    {
      "day": 1317,
      "value": 0.5
    },
    {
      "day": 1318,
      "value": 0.5
    },
    {
      "day": 1319,
      "value": 0.5
    },
    {
      "day": 1320,
      "value": 0.5
    },
    {
      "day": 1321,
      "value": 0.5
    },
    {
      "day": 1322,
      "value": 0.5
    },
    {
      "day": 1323,
      "value": 0.5
    },
    {
      "day": 1324,
      "value": 0.5
    },
    {
      "day": 1325,
      "value": 0.5
    },
    {
      "day": 1326,
      "value": 0.5
    },
    {
      "day": 1327,
      "value": 0.5
    },
    {
      "day": 1328,
      "value": 0.5
    },
    {
      "day": 1329,
      "value": 0.5
    },
    {
      "day": 1330,
      "value": 0.5
    },
    {
      "day": 1331,
      "value": 0.5
    },
    {
      "day": 1332,
      "value": 0.5
    },
    {
      "day": 1333,
      "value": 0.5
    },
    {
      "day": 1334,
      "value": 0.5
    },
    {
      "day": 1335,
      "value": 0.5
    },
    {
      "day": 1336,
      "value": 0.5
    },
    {
      "day": 1337,
      "value": 0.5
    },
    {
      "day": 1338,
      "value": 0.5
    },
    {
      "day": 1339,
      "value": 0.5
    },
    {
      "day": 1340,
      "value": 0.5
    },
    {
      "day": 1341,
      "value": 0.5
    },
    {
      "day": 1342,
      "value": 0.5
    },
    {
      "day": 1343,
      "value": 0.5
    },
    {
      "day": 1344,
      "value": 0.5
    },
    {
      "day": 1345,
      "value": 0.5
    },
    {
      "day": 1346,
      "value": 0.5
    },
    {
      "day": 1347,
      "value": 0.5
    },
    {
      "day": 1348,
      "value": 0.5
    },
    {
      "day": 1349,
      "value": 0.5
    },
    {
      "day": 1350,
      "value": 0.5
    },
    {
      "day": 1351,
      "value": 0.5
    },
    {
      "day": 1352,
      "value": 0.5
    },
    {
      "day": 1353,
      "value": 0.5
    },
    {
      "day": 1354,
      "value": 0.5
    },
    {
      "day": 1355,
      "value": 0.5
    },
    {
      "day": 1356,
      "value": 0.5
    },
    {
      "day": 1357,
      "value": 0.5
    },
    {
      "day": 1358,
      "value": 0.5
    },
    {
      "day": 1359,
      "value": 0.5
    },
    {
      "day": 1360,
      "value": 0.5
    },
    {
      "day": 1361,
      "value": 0.5
    },
    {
      "day": 1362,
      "value": 0.5
    },
    {
      "day": 1363,
      "value": 0.5
    },
    {
      "day": 1364,
      "value": 0.5
    },
    {
      "day": 1365,
      "value": 0.5
    },
    {
      "day": 1366,
      "value": 0.5
    },
    {
      "day": 1367,
      "value": 0.5
    },
    {
      "day": 1368,
      "value": 0.5
    },
    {
      "day": 1369,
      "value": 0.5
    },
    {
      "day": 1370,
      "value": 0.5
    },
    {
      "day": 1371,
      "value": 0.5
    },
    {
      "day": 1372,
      "value": 0.5
    },
    {
      "day": 1373,
      "value": 0.5
    },
    {
      "day": 1374,
      "value": 0.5
    },
    {
      "day": 1375,
      "value": 0.5
    },
    {
      "day": 1376,
      "value": 0.5
    },
    {
      "day": 1377,
      "value": 0.5
    },
    {
      "day": 1378,
      "value": 0.5
    },
    {
      "day": 1379,
      "value": 0.5
    },
    {
      "day": 1380,
      "value": 0.5
    },
    {
      "day": 1381,
      "value": 0.5
    },
    {
      "day": 1382,
      "value": 0.5
    },
    {
      "day": 1383,
      "value": 0.5
    },
    {
      "day": 1384,
      "value": 0.5
    },
    {
      "day": 1385,
      "value": 0.5
    },
    {
      "day": 1386,
      "value": 0.5
    },
    {
      "day": 1387,
      "value": 0.5
    },
    {
      "day": 1388,
      "value": 0.5
    },
    {
      "day": 1389,
      "value": 0.5
    },
    {
      "day": 1390,
      "value": 0.5
    },
    {
      "day": 1391,
      "value": 0.5
    },
    {
      "day": 1392,
      "value": 0.5
    },
    {
      "day": 1393,
      "value": 0.5
    },
    {
      "day": 1394,
      "value": 0.5
    },
    {
      "day": 1395,
      "value": 0.5
    },
    {
      "day": 1396,
      "value": 0.5
    },
    {
      "day": 1397,
      "value": 0.5
    },
    {
      "day": 1398,
      "value": 0.5
    },
    {
      "day": 1399,
      "value": 0.5
    },
    {
      "day": 1400,
      "value": 0.5
    },
    {
      "day": 1401,
      "value": 0.5
    },
    {
      "day": 1402,
      "value": 0.5
    },
    {
      "day": 1403,
      "value": 0.5
    },
    {
      "day": 1404,
      "value": 0.5
    },
    {
      "day": 1405,
      "value": 0.5
    },
    {
      "day": 1406,
      "value": 0.5
    },
    {
      "day": 1407,
      "value": 0.5
    },
    {
      "day": 1408,
      "value": 0.5
    },
    {
      "day": 1409,
      "value": 0.5
    },
    {
      "day": 1410,
      "value": 0.5
    },
    {
      "day": 1411,
      "value": 0.5
    },
    {
      "day": 1412,
      "value": 0.5
    },
    {
      "day": 1413,
      "value": 0.5
    },
    {
      "day": 1414,
      "value": 0.5
    },
    {
      "day": 1415,
      "value": 0.5
    },
    {
      "day": 1416,
      "value": 0.5
    },
    {
      "day": 1417,
      "value": 0.5
    },
    {
      "day": 1418,
      "value": 0.5
    },
    {
      "day": 1419,
      "value": 0.5
    },
    {
      "day": 1420,
      "value": 0.5
    },
    {
      "day": 1421,
      "value": 0.5
    },
    {
      "day": 1422,
      "value": 0.5
    },
    {
      "day": 1423,
      "value": 0.5
    },
    {
      "day": 1424,
      "value": 0.5
    },
    {
      "day": 1425,
      "value": 0.5
    },
    {
      "day": 1426,
      "value": 0.5
    },
    {
      "day": 1427,
      "value": 0.5
    },
    {
      "day": 1428,
      "value": 0.5
    },
    {
      "day": 1429,
      "value": 0.5
    },
    {
      "day": 1430,
      "value": 0.5
    },
    {
      "day": 1431,
      "value": 0.5
    },
    {
      "day": 1432,
      "value": 0.5
    },
    {
      "day": 1433,
      "value": 0.5
    },
    {
      "day": 1434,
      "value": 0.5
    },
    {
      "day": 1435,
      "value": 0.5
    },
    {
      "day": 1436,
      "value": 0.5
    },
    {
      "day": 1437,
      "value": 0.5
    },
    {
      "day": 1438,
      "value": 0.5
    },
    {
      "day": 1439,
      "value": 0.5
    },
    {
      "day": 1440,
      "value": 0.5
    },
    {
      "day": 1441,
      "value": 0.5
    }
  ],
  "createdAt": "2026-03-03T02:30:06.516Z",
  "updatedAt": "2026-03-03T11:39:40.776996"
}